src/__init__.py
src/version.py
src/agents/__init__.py
src/agents/annotation_agent.py
src/agents/assessment_agent.py
src/agents/evaluation_agent.py
src/agents/feedback_summarizer.py
src/agents/feedback_triage_agent.py
src/agents/state.py
src/agents/validation_agent.py
src/agents/vision_agent.py
src/agents/workflow.py
src/api/__init__.py
src/api/main.py
src/api/models.py
src/api/security.py
src/cli/__init__.py
src/cli/client.py
src/cli/config.py
src/cli/main.py
src/cli/output.py
src/cli/commands/__init__.py
src/scripts/__init__.py
src/scripts/process_feedback.py
src/utils/__init__.py
src/utils/error_remediation.py
src/utils/github_client.py
src/utils/hed_comprehensive_guide.py
src/utils/hed_rules.py
src/utils/image_processing.py
src/utils/json_schema_loader.py
src/utils/openrouter_llm.py
src/utils/schema_loader.py
src/validation/__init__.py
src/validation/hed_validator.py
hedit-0.6.1a2.dist-info/METADATA
hedit-0.6.1a2.dist-info/WHEEL
hedit-0.6.1a2.dist-info/entry_points.txt
hedit-0.6.1a2.dist-info/top_level.txt
hedit-0.6.1a2.dist-info/RECORD
