Metadata-Version: 2.4
Name: hedit
Version: 0.6.1a2
Summary: Multi-agent system for HED annotation generation and validation
Author-email: Annotation Garden Initiative <info@annotation.garden>
License-Expression: MIT
Project-URL: Homepage, https://annotation.garden/hedit
Project-URL: Documentation, https://github.com/Annotation-Garden/hedit#readme
Project-URL: Repository, https://github.com/Annotation-Garden/hedit
Project-URL: Issues, https://github.com/Annotation-Garden/hedit/issues
Keywords: hed,annotation,neuroscience,bids,cli
Classifier: Development Status :: 4 - Beta
Classifier: Environment :: Console
Classifier: Intended Audience :: Science/Research
Classifier: Operating System :: OS Independent
Classifier: Programming Language :: Python :: 3
Classifier: Programming Language :: Python :: 3.12
Classifier: Topic :: Scientific/Engineering
Requires-Python: >=3.12
Requires-Dist: langgraph>=0.2.0
Requires-Dist: langchain>=0.3.0
Requires-Dist: langchain-community>=0.3.0
Requires-Dist: langchain-core>=0.3.0
Requires-Dist: langchain-openai>=0.3.0
Requires-Dist: fastapi>=0.121.0
Requires-Dist: uvicorn[standard]>=0.38.0
Requires-Dist: pydantic>=2.12.0
Requires-Dist: python-multipart>=0.0.17
Requires-Dist: aiofiles>=25.1.0
Requires-Dist: httpx>=0.28.0
Requires-Dist: hedtools>=0.5.0
Requires-Dist: lxml>=5.3.0
Requires-Dist: beautifulsoup4>=4.12.3
Requires-Dist: pillow>=11.0.0
Requires-Dist: typer>=0.20.0
Requires-Dist: rich>=14.0.0
Requires-Dist: platformdirs>=4.5.0
Requires-Dist: pyyaml>=6.0.2
Provides-Extra: dev
Requires-Dist: pytest>=8.3.0; extra == "dev"
Requires-Dist: pytest-cov>=5.0.0; extra == "dev"
Requires-Dist: pytest-asyncio>=0.24.0; extra == "dev"
Requires-Dist: ruff>=0.7.0; extra == "dev"
Requires-Dist: black>=24.8.0; extra == "dev"
Requires-Dist: mypy>=1.11.0; extra == "dev"
